reinmax/__init__.py
reinmax/reinmax.py
reinmax-0.1.0.dist-info/METADATA
reinmax-0.1.0.dist-info/WHEEL
reinmax-0.1.0.dist-info/top_level.txt
reinmax-0.1.0.dist-info/RECORD
