Metadata-Version: 2.1
Name: reinmax
Version: 0.1.0
Summary: ReinMax Algorithm
Home-page: https://github.com/microsoft/reinmax
Author: Lucas Liu
Author-email: llychinalz@gmail.com
License: MIT
Platform: UNKNOWN
Classifier: Development Status :: 2 - Pre-Alpha
Classifier: Intended Audience :: Developers
Classifier: Natural Language :: English
Classifier: Programming Language :: Python :: 3.7
Classifier: Programming Language :: Python :: 3.8
Classifier: Programming Language :: Python :: 3.9
Requires-Dist: torch
